aspplea/__init__.py
aspplea/exact.py
aspplea/heuristic.py
aspplea/salesman.py
aspplea-0.0.3.dist-info/LICENSE
aspplea-0.0.3.dist-info/METADATA
aspplea-0.0.3.dist-info/WHEEL
aspplea-0.0.3.dist-info/top_level.txt
aspplea-0.0.3.dist-info/RECORD
