Metadata-Version: 2.1
Name: aspplea
Version: 0.0.3
Summary: ASPP course project package 'Traveling Salesperson'
Home-page: https://github.com/LeaHohmann/TravelingSalesperson
Author: Lea Hohmann
Author-email: lea.hohmann@outlook.de
License: UNKNOWN
Platform: UNKNOWN
Classifier: Programming Language :: Python :: 3
Classifier: License :: OSI Approved :: MIT License
Classifier: Operating System :: OS Independent
Requires-Python: >=3.4
Requires-Dist: numpy
Requires-Dist: pandas
